py_netatmo_truetemp/__init__.py
py_netatmo_truetemp/_version.py
py_netatmo_truetemp/api_client.py
py_netatmo_truetemp/auth_manager.py
py_netatmo_truetemp/constants.py
py_netatmo_truetemp/cookie_store.py
py_netatmo_truetemp/exceptions.py
py_netatmo_truetemp/home_service.py
py_netatmo_truetemp/logger.py
py_netatmo_truetemp/netatmo_api.py
py_netatmo_truetemp/py.typed
py_netatmo_truetemp/thermostat_service.py
py_netatmo_truetemp/types.py
py_netatmo_truetemp/validators.py
py_netatmo_truetemp-0.3.1.dist-info/METADATA
py_netatmo_truetemp-0.3.1.dist-info/WHEEL
py_netatmo_truetemp-0.3.1.dist-info/licenses/LICENSE
py_netatmo_truetemp-0.3.1.dist-info/RECORD
