Metadata-Version: 2.4
Name: py-netatmo-truetemp
Version: 0.3.1
Summary: Netatmo's missing true temperature API - set real room temps programmatically
Project-URL: Homepage, https://github.com/py-netatmo-unofficial/py-netatmo-truetemp
Project-URL: Repository, https://github.com/py-netatmo-unofficial/py-netatmo-truetemp
Project-URL: Issues, https://github.com/py-netatmo-unofficial/py-netatmo-truetemp/issues
Project-URL: Changelog, https://github.com/py-netatmo-unofficial/py-netatmo-truetemp/blob/main/CHANGELOG.md
Project-URL: Documentation, https://github.com/py-netatmo-unofficial/py-netatmo-truetemp#readme
Author-email: P4uLT <P4uLT@users.noreply.github.com>
Maintainer-email: P4uLT <P4uLT@users.noreply.github.com>
License: MIT
License-File: LICENSE
Keywords: api-client,home-automation,iot,netatmo,python-library,sdk,smart-home,temperature-control,thermostat,true-temperature,truetemp
Classifier: Development Status :: 4 - Beta
Classifier: Intended Audience :: Developers
Classifier: License :: OSI Approved :: MIT License
Classifier: Operating System :: OS Independent
Classifier: Programming Language :: Python :: 3
Classifier: Programming Language :: Python :: 3 :: Only
Classifier: Programming Language :: Python :: 3.13
Classifier: Topic :: Home Automation
Classifier: Topic :: Software Development :: Libraries :: Python Modules
Classifier: Typing :: Typed
Requires-Python: >=3.13
Requires-Dist: platformdirs>=4.0.0
Requires-Dist: requests==2.32.5
